rtl/lane_bitslip.sv

`timescale 1ns/1ps

module lane_bitslip #(
    parameter int LANES = 8
) (
    input  logic              dco_clk,
    input  logic              rst_n,           // active-low reset

    input  logic [LANES-1:0]  in_rise,         // from DDR capture (posedge)
    input  logic [LANES-1:0]  in_fall,         // from DDR capture (negedge)

    input  logic [LANES-1:0]  bitslip_pulse,   // toggle request (pulse), synchronous to dco_clk

    output logic [LANES-1:0]  out_rise,        // corrected, registered
    output logic [LANES-1:0]  out_fall         // corrected, registered
);

    logic [LANES-1:0] slip_offset;   // 0=normal, 1=half-bit slipped
    logic [LANES-1:0] prev_fall;     // stores f_k to be used as f_(k-1) next posedge
    logic [LANES-1:0] rise_hold;     // holds current rise (r_k) for use at negedge

    
    always_ff @(posedge dco_clk or negedge rst_n) begin
        if (!rst_n) begin
            slip_offset <= '0;
            rise_hold <= '0;
            out_rise  <= '0;
        end else begin
            slip_offset <= slip_offset ^ bitslip_pulse; 
            rise_hold <= in_rise;
            out_rise <= (slip_offset) ? prev_fall : in_rise;
        end
    end


    
    always_ff @(negedge dco_clk or negedge rst_n) begin
        if (!rst_n) begin
            prev_fall <= '0;
            out_fall  <= '0;
        end else begin
          
            out_fall <= (slip_offset) ? rise_hold : in_fall;

            
            prev_fall <= in_fall;
        end
    end


endmodule

tb/tb_lane_bitslip.sv
`timescale 1ns/1ps

module tb_lane_bitslip;

  localparam int LANES = 2;     
  logic              dco_clk;
  logic              rst_n;

  logic [LANES-1:0]  in_rise;
  logic [LANES-1:0]  in_fall;
  logic [LANES-1:0]  bitslip_pulse;

  logic [LANES-1:0]  out_rise;
  logic [LANES-1:0]  out_fall;

  // DUT
  lane_bitslip #(.LANES(LANES)) dut (
    .dco_clk(dco_clk),
    .rst_n(rst_n),
    .in_rise(in_rise),
    .in_fall(in_fall),
    .bitslip_pulse(bitslip_pulse),
    .out_rise(out_rise),
    .out_fall(out_fall)
  );

  // clock: 10ns period
  initial dco_clk = 1'b0;
  always  #5 dco_clk = ~dco_clk;

  // VCD
  initial begin
    $dumpfile("waves_bitslip_adv.vcd");
    $dumpvars(0, tb_lane_bitslip);
  end

  task automatic expect_eq(input logic [LANES-1:0] got,
                           input logic [LANES-1:0] exp,
                           input string msg);
    if (got !== exp) begin
      $display("FAIL @ t=%0t : %s | got=%b exp=%b", $time, msg, got, exp);
      $fatal(1);
    end else begin
      $display("PASS @ t=%0t : %s | %b", $time, msg, got);
    end
  endtask

  
  task automatic drive_cycle(input int k);
    
    in_rise[0] = k[0];
    in_rise[1] = k[1];
    in_fall[0] = ~k[0];
    in_fall[1] = ~k[1];
  endtask

  
  logic [LANES-1:0] prev_fall_exp;
  logic [LANES-1:0] slip_offset_exp;

  initial begin
    
    rst_n         = 1'b0;
    in_rise       = '0;
    in_fall       = '0;
    bitslip_pulse = '0;

    prev_fall_exp  = '0;
    slip_offset_exp = '0;

    
    repeat (2) @(posedge dco_clk);
    rst_n = 1'b1;
    $display("Released reset @ t=%0t", $time);

    // -------------------------
    // Phase A: offset=0 (normal)
    // -------------------------
    // k=0..2
    for (int k = 0; k < 3; k++) begin
      
      drive_cycle(k);
      #1;

      @(posedge dco_clk);
      #1ps;
      expect_eq(out_rise, in_rise, $sformatf("normal: out_rise=r_%0d", k));

      
      #1;
      @(negedge dco_clk);
      #1ps;
      
      expect_eq(out_fall, in_fall, $sformatf("normal: out_fall=f_%0d", k));

      
      prev_fall_exp = in_fall;
    end

    // -------------------------
    // Phase B: Toggle slip_offset (bitslip_pulse)
    // -------------------------
    drive_cycle(3);
    bitslip_pulse = '1; 
    #1;
    @(posedge dco_clk);
    #1ps;
    bitslip_pulse = '0;
    expect_eq(out_rise, in_rise, "toggle edge: still normal out_rise = r_3");

    #1;
    @(negedge dco_clk);
    #1ps;
    expect_eq(out_fall, in_rise, "slipped: out_fall = r_3");

    
    prev_fall_exp = in_fall;

    
    drive_cycle(4);
    #1;
    @(posedge dco_clk); #0;
    #1ps;
    expect_eq(out_rise, prev_fall_exp, "slipped: out_rise = f_3");

    #1;
    @(negedge dco_clk); #0;
    #1ps;
    expect_eq(out_fall, in_rise, "slipped: out_fall = r_4");

    $display("ALL TESTS PASSED ✅");
    #20;
    $finish;
  end

endmodule

waves_bitslip_adv.vcd
$date
	Mon Jan 12 16:05:54 2026
$end
$version
	Icarus Verilog
$end
$timescale
	1ps
$end
$scope module tb_lane_bitslip $end
$var wire 2 ! out_rise [1:0] $end
$var wire 2 " out_fall [1:0] $end
$var parameter 32 # LANES $end
$var reg 2 $ bitslip_pulse [1:0] $end
$var reg 1 % dco_clk $end
$var reg 2 & in_fall [1:0] $end
$var reg 2 ' in_rise [1:0] $end
$var reg 2 ( prev_fall_exp [1:0] $end
$var reg 1 ) rst_n $end
$var reg 2 * slip_offset_exp [1:0] $end
$scope module dut $end
$var wire 2 + bitslip_pulse [1:0] $end
$var wire 1 % dco_clk $end
$var wire 2 , in_fall [1:0] $end
$var wire 2 - in_rise [1:0] $end
$var wire 1 ) rst_n $end
$var parameter 32 . LANES $end
$var reg 2 / out_fall [1:0] $end
$var reg 2 0 out_rise [1:0] $end
$var reg 2 1 prev_fall [1:0] $end
$var reg 2 2 rise_hold [1:0] $end
$var reg 2 3 slip_offset [1:0] $end
$upscope $end
$scope begin $ivl_for_loop0 $end
$var integer 32 4 k [31:0] $end
$upscope $end
$scope task drive_cycle $end
$upscope $end
$scope task expect_eq $end
$upscope $end
$upscope $end
$enddefinitions $end
$comment Show the parameter values. $end
$dumpall
b10 .
b10 #
$end
#0
$dumpvars
b0 4
b0 3
b0 2
b0 1
b0 0
b0 /
b0 -
b0 ,
b0 +
b0 *
0)
b0 (
b0 '
b0 &
0%
b0 $
b0 "
b0 !
$end
#5000
1%
#10000
0%
#15000
b11 &
b11 ,
1)
1%
#20000
b11 1
b11 "
b11 /
0%
#25000
1%
#30000
0%
#30001
b10 &
b10 ,
b1 '
b1 -
b1 4
b11 (
#35000
b1 !
b1 0
b1 2
1%
#40000
b10 1
b10 "
b10 /
0%
#40001
b1 &
b1 ,
b10 '
b10 -
b10 4
b10 (
#45000
b10 !
b10 0
b10 2
1%
#50000
b1 1
b1 "
b1 /
0%
#50001
b11 $
b11 +
b0 &
b0 ,
b11 '
b11 -
b11 4
b1 (
#55000
b11 !
b11 0
b11 2
b11 3
1%
#55001
b0 $
b0 +
#60000
b0 1
b11 "
b11 /
0%
#60001
b11 &
b11 ,
b0 '
b0 -
b0 (
#65000
b0 !
b0 0
b0 2
1%
#70000
b11 1
b0 "
b0 /
0%
#75000
b11 !
b11 0
1%
