rtl/lane_bitslip.sv

`timescale 1ns/1ps

module lane_bitslip #(
    parameter int LANES = 8
) (
    input  logic              dco_clk,
    input  logic              rst_n,           // active-low reset

    input  logic [LANES-1:0]  in_rise,         // from DDR capture (posedge)
    input  logic [LANES-1:0]  in_fall,         // from DDR capture (negedge)

    input  logic [LANES-1:0]  bitslip_pulse,   // toggle request (pulse), synchronous to dco_clk

    output logic [LANES-1:0]  out_rise,        // corrected, registered
    output logic [LANES-1:0]  out_fall         // corrected, registered
);

    logic [LANES-1:0] slip_offset;   // 0=normal, 1=half-bit slipped
    logic [LANES-1:0] prev_fall;     // stores f_k to be used as f_(k-1) next posedge
    logic [LANES-1:0] rise_hold;     // holds current rise (r_k) for use at negedge

    
    always_ff @(posedge dco_clk or negedge rst_n) begin
        if (!rst_n) begin
            slip_offset <= '0;
            rise_hold <= '0;
            out_rise  <= '0;
        end else begin
            slip_offset <= slip_offset ^ bitslip_pulse; 
            rise_hold <= in_rise;
            out_rise <= (slip_offset) ? prev_fall : in_rise;
        end
    end


    
    always_ff @(negedge dco_clk or negedge rst_n) begin
        if (!rst_n) begin
            prev_fall <= '0;
            out_fall  <= '0;
        end else begin
          
            out_fall <= (slip_offset) ? rise_hold : in_fall;

            
            prev_fall <= in_fall;
        end
    end


endmodule

tb/tb_lane_bitslip.sv
 `timescale 1ns/1ps

module tb_lane_bitslip_1lane;

  localparam int LANES = 1;

  logic              dco_clk;
  logic              rst_n;

  logic [LANES-1:0]  in_rise;
  logic [LANES-1:0]  in_fall;
  logic [LANES-1:0]  bitslip_pulse;

  logic [LANES-1:0]  out_rise;
  logic [LANES-1:0]  out_fall;

  // DUT
  lane_bitslip #(.LANES(LANES)) dut (
    .dco_clk(dco_clk),
    .rst_n(rst_n),
    .in_rise(in_rise),
    .in_fall(in_fall),
    .bitslip_pulse(bitslip_pulse),
    .out_rise(out_rise),
    .out_fall(out_fall)
  );

  // 10ns period clock
  initial dco_clk = 1'b0;
  always  #5 dco_clk = ~dco_clk;

  // VCD
  initial begin
    $dumpfile("waves_bitslip_1lane.vcd");
    $dumpvars(0, tb_lane_bitslip_1lane);
  end

  // Simple pattern generator: r_k = k[0], f_k = ~k[0]
  int k;
  logic prev_fall;

  initial begin
    // init
    rst_n         = 1'b0;
    in_rise       = '0;
    in_fall       = '0;
    bitslip_pulse = '0;
    prev_fall     = 1'b0;

    // hold reset for 2 posedges
    repeat (2) @(posedge dco_clk);
    rst_n = 1'b1;

    // -------------------------
    // Phase A: no slip (expect passthrough)
    // -------------------------
    for (k = 0; k < 4; k = k + 1) begin
      in_rise[0] = k[0];
      in_fall[0] = ~k[0];

      @(posedge dco_clk);
      #1ps;
      if (out_rise[0] !== in_rise[0]) begin
        $display("FAIL normal out_rise @t=%0t k=%0d got=%b exp=%b", $time, k, out_rise[0], in_rise[0]);
        $fatal(1);
      end

      @(negedge dco_clk);
      #1ps;
      if (out_fall[0] !== in_fall[0]) begin
        $display("FAIL normal out_fall @t=%0t k=%0d got=%b exp=%b", $time, k, out_fall[0], in_fall[0]);
        $fatal(1);
      end

      prev_fall = in_fall[0];
    end

    // -------------------------
    // Phase B: toggle slip on next posedge
    // Expect:
    //   - At toggle posedge: out_rise still normal (uses old slip)
    //   - At following negedge: out_fall = rise_hold (current r_k)
    //   - Next posedge: out_rise = prev_fall from previous cycle
    // -------------------------
    k = 4;
    in_rise[0] = k[0];
    in_fall[0] = ~k[0];

    bitslip_pulse[0] = 1'b1;
    @(posedge dco_clk);
    #1ps;
    bitslip_pulse[0] = 1'b0;

    #1ps;
    // still normal on this edge (depends on implementation order; this matches common intent)
    if (out_rise[0] !== in_rise[0]) begin
      $display("FAIL toggle-edge out_rise @t=%0t k=%0d got=%b exp=%b", $time, k, out_rise[0], in_rise[0]);
      $fatal(1);
    end

    @(negedge dco_clk);
    #1ps;
    // slipped: out_fall should become rise_hold == current in_rise
    if (out_fall[0] !== in_rise[0]) begin
      $display("FAIL slipped out_fall @t=%0t k=%0d got=%b exp=%b", $time, k, out_fall[0], in_rise[0]);
      $fatal(1);
    end

    // advance one more cycle with slip active
    prev_fall = in_fall[0];
    k = 5;
    in_rise[0] = k[0];
    in_fall[0] = ~k[0];

    @(posedge dco_clk);
    #1ps;
    // slipped: out_rise should be previous fall
    if (out_rise[0] !== prev_fall) begin
      $display("FAIL slipped out_rise @t=%0t k=%0d got=%b exp=%b", $time, k, out_rise[0], prev_fall);
      $fatal(1);
    end

    @(negedge dco_clk);
    #1ps;
    // slipped: out_fall should be current rise
    if (out_fall[0] !== in_rise[0]) begin
      $display("FAIL slipped out_fall2 @t=%0t k=%0d got=%b exp=%b", $time, k, out_fall[0], in_rise[0]);
      $fatal(1);
    end

    $display("ALL TESTS PASSED ✅");
    #20;
    $finish;
  end

endmodule

waves_bitslip_1lane.vcd
$date
	Mon Jan 12 16:14:01 2026
$end
$version
	Icarus Verilog
$end
$timescale
	1ps
$end
$scope module tb_lane_bitslip_1lane $end
$var wire 1 ! out_rise $end
$var wire 1 " out_fall $end
$var parameter 32 # LANES $end
$var reg 1 $ bitslip_pulse $end
$var reg 1 % dco_clk $end
$var reg 1 & in_fall $end
$var reg 1 ' in_rise $end
$var reg 1 ( prev_fall $end
$var reg 1 ) rst_n $end
$var integer 32 * k [31:0] $end
$scope module dut $end
$var wire 1 $ bitslip_pulse $end
$var wire 1 % dco_clk $end
$var wire 1 & in_fall $end
$var wire 1 ' in_rise $end
$var wire 1 ) rst_n $end
$var parameter 32 + LANES $end
$var reg 1 " out_fall $end
$var reg 1 ! out_rise $end
$var reg 1 , prev_fall $end
$var reg 1 - rise_hold $end
$var reg 1 . slip_offset $end
$upscope $end
$upscope $end
$enddefinitions $end
$comment Show the parameter values. $end
$dumpall
b1 +
b1 #
$end
#0
$dumpvars
0.
0-
0,
b0 *
0)
0(
0'
0&
0%
0$
0"
0!
$end
#5000
1%
#10000
0%
#15000
1&
1)
1%
#20000
1,
1"
0%
#25000
1%
#30000
0%
#30001
0&
1'
b1 *
1(
#35000
1!
1-
1%
#40000
0,
0"
0%
#40001
1&
0'
b10 *
0(
#45000
0!
0-
1%
#50000
1,
1"
0%
#50001
0&
1'
b11 *
1(
#55000
1!
1-
1%
#60000
0,
0"
0%
#60001
1$
1&
0'
b100 *
0(
#65000
0!
0-
1.
1%
#65001
0$
#70000
1,
0%
#70001
0&
1'
b101 *
1(
#75000
1!
1-
1%
#80000
0,
1"
0%
#85000
0!
1%
